{
  "name": "Pantone Pewter (Dark)",
  "type": "dark",
  "semanticHighlighting": true,
  "semanticTokenColors": {
    "variable.declaration": {
      "foreground": "#e3e4e4"
    },
    "variable.readonly": {
      "foreground": "#76ff7b",
      "bold": true
    },
    "parameter.declaration": {
      "foreground": "#e3e4e4",
      "italic": true
    },
    "function.declaration": {
      "foreground": "#decdbe",
      "bold": true
    },
    "function.defaultLibrary": {
      "foreground": "#decdbe"
    },
    "type": {
      "foreground": "#00b5cc",
      "italic": true
    },
    "type.defaultLibrary": {
      "foreground": "#00b5cc",
      "italic": true
    },
    "class": {
      "foreground": "#88b04b",
      "bold": true,
      "italic": true
    },
    "interface": {
      "foreground": "#00b5cc",
      "italic": true
    },
    "enum": {
      "foreground": "#00b5cc",
      "italic": true
    },
    "enumMember": {
      "foreground": "#76ff7b",
      "bold": true
    },
    "namespace": {
      "foreground": "#00b5cc"
    },
    "property.readonly": {
      "foreground": "#76ff7b",
      "bold": true
    }
  },
  "colors": {
    "editor.background": "#121313",
    "editor.foreground": "#e3e4e4",
    "editorCursor.foreground": "#9a9e9d",
    "editor.selectionBackground": "#9a9e9d4d",
    "editor.inactiveSelectionBackground": "#9a9e9d26",
    "editor.lineHighlightBackground": "#9a9e9d1a",
    "editor.lineHighlightBorder": "#9a9e9d00",
    "editor.findMatchBackground": "#5f4b8b66",
    "editor.findMatchHighlightBackground": "#5f4b8b33",
    "editor.wordHighlightBackground": "#9a9e9d33",
    "editorBracketMatch.background": "#9a9e9d40",
    "editorBracketMatch.border": "#9a9e9d99",
    "editorIndentGuide.background": "#e3e4e414",
    "editorIndentGuide.activeBackground": "#e3e4e433",
    "editorWhitespace.foreground": "#e3e4e41a",
    "editorRuler.foreground": "#e3e4e414",
    "editorLineNumber.foreground": "#9a9e9d",
    "editorLineNumber.activeForeground": "#e3e4e4",
    "editorGutter.addedBackground": "#88b04b",
    "editorGutter.modifiedBackground": "#efc050",
    "editorGutter.deletedBackground": "#dd4132",
    "editorError.foreground": "#dd4132",
    "editorWarning.foreground": "#efc050",
    "editorInfo.foreground": "#d94f70",
    "sideBar.background": "#222323",
    "sideBar.foreground": "#e3e4e4",
    "sideBar.border": "#2e2f2f",
    "sideBarTitle.foreground": "#e3e4e4",
    "sideBarSectionHeader.background": "#9a9e9d26",
    "sideBarSectionHeader.foreground": "#e3e4e4",
    "activityBar.background": "#1a1b1b",
    "activityBar.foreground": "#9a9e9d",
    "activityBar.inactiveForeground": "#9a9e9d",
    "activityBar.border": "#2e2f2f",
    "activityBarBadge.background": "#d94f70",
    "activityBarBadge.foreground": "#f7f7f7",
    "titleBar.activeBackground": "#1a1b1b",
    "titleBar.activeForeground": "#e3e4e4",
    "titleBar.inactiveBackground": "#1a1b1b",
    "titleBar.inactiveForeground": "#9a9e9d",
    "titleBar.border": "#2e2f2f",
    "tab.activeBackground": "#121313",
    "tab.activeForeground": "#e3e4e4",
    "tab.inactiveBackground": "#1a1b1b",
    "tab.inactiveForeground": "#9a9e9d",
    "tab.activeBorder": "#9a9e9d",
    "tab.activeBorderTop": "#9a9e9d00",
    "tab.border": "#2e2f2f",
    "editorGroupHeader.tabsBackground": "#1a1b1b",
    "editorGroupHeader.tabsBorder": "#2e2f2f",
    "editorGroup.border": "#2e2f2f",
    "statusBar.background": "#5c5f5e",
    "statusBar.foreground": "#c2c5c4",
    "statusBar.border": "#2e2f2f",
    "statusBar.debuggingBackground": "#d94f70",
    "statusBar.debuggingForeground": "#f7f7f7",
    "statusBar.noFolderBackground": "#1a1b1b",
    "statusBarItem.hoverBackground": "#9a9e9d4d",
    "statusBarItem.remoteBackground": "#9a9e9d",
    "statusBarItem.remoteForeground": "#171818",
    "input.background": "#1a1b1b",
    "input.foreground": "#e3e4e4",
    "input.border": "#2e2f2f",
    "input.placeholderForeground": "#9a9e9d",
    "inputOption.activeBorder": "#9a9e9d",
    "inputValidation.errorBorder": "#dd4132",
    "inputValidation.warningBorder": "#efc050",
    "inputValidation.infoBorder": "#d94f70",
    "dropdown.background": "#1a1b1b",
    "dropdown.foreground": "#e3e4e4",
    "dropdown.border": "#2e2f2f",
    "list.activeSelectionBackground": "#9a9e9d4d",
    "list.activeSelectionForeground": "#e3e4e4",
    "list.hoverBackground": "#9a9e9d26",
    "list.inactiveSelectionBackground": "#9a9e9d26",
    "list.focusBackground": "#9a9e9d33",
    "list.highlightForeground": "#9a9e9d",
    "button.background": "#9a9e9d",
    "button.foreground": "#171818",
    "button.hoverBackground": "#a4a8a7",
    "button.secondaryBackground": "#222323",
    "button.secondaryForeground": "#e3e4e4",
    "badge.background": "#9a9e9d",
    "badge.foreground": "#171818",
    "scrollbar.shadow": "#0f101045",
    "scrollbarSlider.background": "#e3e4e41f",
    "scrollbarSlider.hoverBackground": "#e3e4e440",
    "scrollbarSlider.activeBackground": "#e3e4e459",
    "minimap.background": "#121313",
    "minimap.findMatchHighlight": "#5f4b8b99",
    "minimap.selectionHighlight": "#9a9e9d66",
    "panel.background": "#1a1b1b",
    "panel.border": "#2e2f2f",
    "panelTitle.activeBorder": "#9a9e9d",
    "panelTitle.activeForeground": "#e3e4e4",
    "panelTitle.inactiveForeground": "#9a9e9d",
    "terminal.background": "#1a1b1b",
    "terminal.foreground": "#e3e4e4",
    "terminalCursor.foreground": "#9a9e9d",
    "terminal.ansiBlack": "#121313",
    "terminal.ansiRed": "#dd4132",
    "terminal.ansiGreen": "#88b04b",
    "terminal.ansiYellow": "#efc050",
    "terminal.ansiBlue": "#55758f",
    "terminal.ansiMagenta": "#b163a3",
    "terminal.ansiCyan": "#45b5aa",
    "terminal.ansiWhite": "#e3e4e4",
    "terminal.ansiBrightBlack": "#9a9e9d",
    "terminal.ansiBrightRed": "#e25e51",
    "terminal.ansiBrightGreen": "#9abc66",
    "terminal.ansiBrightYellow": "#f1c96a",
    "terminal.ansiBrightBlue": "#4b79a1",
    "terminal.ansiBrightMagenta": "#bd7ab1",
    "terminal.ansiBrightCyan": "#61c0b7",
    "terminal.ansiBrightWhite": "#f7f7f7",
    "gitDecoration.addedResourceForeground": "#88b04b",
    "gitDecoration.modifiedResourceForeground": "#efc050",
    "gitDecoration.deletedResourceForeground": "#dd4132",
    "gitDecoration.untrackedResourceForeground": "#88b04b",
    "gitDecoration.conflictingResourceForeground": "#ff6f61",
    "gitDecoration.ignoredResourceForeground": "#9a9e9d",
    "breadcrumb.foreground": "#9a9e9d",
    "breadcrumb.focusForeground": "#e3e4e4",
    "breadcrumb.activeSelectionForeground": "#e3e4e4",
    "notifications.background": "#222323",
    "notifications.foreground": "#e3e4e4",
    "notificationLink.foreground": "#9a9e9d",
    "peekView.border": "#9a9e9d",
    "peekViewEditor.background": "#1a1b1b",
    "peekViewResult.background": "#222323",
    "peekViewTitle.background": "#1a1b1b",
    "editorWidget.background": "#1a1b1b",
    "editorWidget.border": "#2e2f2f",
    "editorSuggestWidget.selectedBackground": "#9a9e9d40",
    "focusBorder": "#9a9e9d99",
    "selection.background": "#9a9e9d4d",
    "textLink.foreground": "#d94f70",
    "textLink.activeForeground": "#df6985",
    "progressBar.background": "#9a9e9d",
    "icon.foreground": "#9a9e9d",
    "descriptionForeground": "#9a9e9d"
  },
  "tokenColors": [
    {
      "name": "Comments",
      "scope": [
        "comment",
        "comment.line",
        "comment.block",
        "comment.block.documentation",
        "punctuation.definition.comment"
      ],
      "settings": {
        "foreground": "#9a9e9d",
        "fontStyle": "italic"
      }
    },
    {
      "name": "Keywords",
      "scope": [
        "keyword",
        "keyword.control",
        "keyword.control.conditional",
        "keyword.control.loop",
        "keyword.control.flow",
        "keyword.control.import",
        "keyword.control.export",
        "keyword.control.from"
      ],
      "settings": {
        "foreground": "#9a9e9d",
        "fontStyle": "bold"
      }
    },
    {
      "name": "Keyword operators",
      "scope": [
        "keyword.operator.new",
        "keyword.operator.expression",
        "keyword.operator.instanceof",
        "keyword.operator.typeof",
        "keyword.operator.logical",
        "keyword.operator.delete"
      ],
      "settings": {
        "foreground": "#9a9e9d",
        "fontStyle": "bold"
      }
    },
    {
      "name": "Storage type (class, function, var, let, const)",
      "scope": [
        "storage.type",
        "storage.modifier"
      ],
      "settings": {
        "foreground": "#9a9e9d",
        "fontStyle": "bold"
      }
    },
    {
      "name": "Strings",
      "scope": [
        "string",
        "string.quoted",
        "string.quoted.single",
        "string.quoted.double",
        "string.quoted.triple",
        "string.template",
        "string.quoted.other"
      ],
      "settings": {
        "foreground": "#d94f70",
        "fontStyle": ""
      }
    },
    {
      "name": "String interpolation",
      "scope": [
        "string.interpolated",
        "punctuation.definition.template-expression",
        "punctuation.section.embedded"
      ],
      "settings": {
        "foreground": "#9a9e9d",
        "fontStyle": ""
      }
    },
    {
      "name": "Regular expressions",
      "scope": [
        "string.regexp"
      ],
      "settings": {
        "foreground": "#d94f70",
        "fontStyle": ""
      }
    },
    {
      "name": "Numbers",
      "scope": [
        "constant.numeric",
        "constant.numeric.integer",
        "constant.numeric.float",
        "constant.numeric.hex"
      ],
      "settings": {
        "foreground": "#8d7dac",
        "fontStyle": ""
      }
    },
    {
      "name": "Language constants (true, false, null)",
      "scope": [
        "constant.language",
        "constant.language.boolean",
        "constant.language.null",
        "constant.language.undefined"
      ],
      "settings": {
        "foreground": "#76ff7b",
        "fontStyle": "bold"
      }
    },
    {
      "name": "Other constants (ALL_CAPS, enums)",
      "scope": [
        "variable.other.constant",
        "variable.other.enummember"
      ],
      "settings": {
        "foreground": "#76ff7b",
        "fontStyle": "bold"
      }
    },
    {
      "name": "Escape characters",
      "scope": [
        "constant.character.escape"
      ],
      "settings": {
        "foreground": "#a9adac",
        "fontStyle": ""
      }
    },
    {
      "name": "Type names and interfaces",
      "scope": [
        "entity.name.type",
        "entity.name.type.class",
        "entity.name.type.interface",
        "entity.name.type.enum",
        "entity.name.type.alias",
        "entity.name.type.module",
        "support.type",
        "support.type.builtin"
      ],
      "settings": {
        "foreground": "#00b5cc",
        "fontStyle": "italic"
      }
    },
    {
      "name": "Type parameters (generics <T>)",
      "scope": [
        "entity.name.type.parameter"
      ],
      "settings": {
        "foreground": "#00b5cc",
        "fontStyle": "italic"
      }
    },
    {
      "name": "Function declarations",
      "scope": [
        "entity.name.function",
        "meta.function entity.name.function"
      ],
      "settings": {
        "foreground": "#decdbe",
        "fontStyle": "bold"
      }
    },
    {
      "name": "Function calls",
      "scope": [
        "meta.function-call entity.name.function",
        "support.function"
      ],
      "settings": {
        "foreground": "#decdbe",
        "fontStyle": ""
      }
    },
    {
      "name": "Method calls",
      "scope": [
        "meta.method-call entity.name.function",
        "entity.name.function.member"
      ],
      "settings": {
        "foreground": "#decdbe",
        "fontStyle": ""
      }
    },
    {
      "name": "Variables",
      "scope": [
        "variable",
        "variable.other",
        "variable.other.readwrite"
      ],
      "settings": {
        "foreground": "#e3e4e4",
        "fontStyle": ""
      }
    },
    {
      "name": "Parameters",
      "scope": [
        "variable.parameter"
      ],
      "settings": {
        "foreground": "#e3e4e4",
        "fontStyle": "italic"
      }
    },
    {
      "name": "Language variables (this, self, super)",
      "scope": [
        "variable.language",
        "variable.language.this",
        "variable.language.self",
        "variable.language.super"
      ],
      "settings": {
        "foreground": "#9a9e9d",
        "fontStyle": "italic"
      }
    },
    {
      "name": "Object properties",
      "scope": [
        "variable.other.property",
        "variable.other.object.property",
        "meta.object-literal.key"
      ],
      "settings": {
        "foreground": "#e3e4e4",
        "fontStyle": ""
      }
    },
    {
      "name": "Class names",
      "scope": [
        "entity.name.class",
        "entity.name.type.class",
        "support.class"
      ],
      "settings": {
        "foreground": "#88b04b",
        "fontStyle": "bold italic"
      }
    },
    {
      "name": "Inherited classes",
      "scope": [
        "entity.other.inherited-class"
      ],
      "settings": {
        "foreground": "#88b04b",
        "fontStyle": "italic"
      }
    },
    {
      "name": "HTML/XML tags",
      "scope": [
        "entity.name.tag",
        "punctuation.definition.tag"
      ],
      "settings": {
        "foreground": "#9a9e9d",
        "fontStyle": "bold"
      }
    },
    {
      "name": "HTML/XML attributes",
      "scope": [
        "entity.other.attribute-name"
      ],
      "settings": {
        "foreground": "#decdbe",
        "fontStyle": "italic"
      }
    },
    {
      "name": "Operators",
      "scope": [
        "keyword.operator",
        "keyword.operator.arithmetic",
        "keyword.operator.assignment",
        "keyword.operator.comparison",
        "keyword.operator.ternary"
      ],
      "settings": {
        "foreground": "#a9adac",
        "fontStyle": ""
      }
    },
    {
      "name": "Punctuation",
      "scope": [
        "punctuation",
        "punctuation.separator",
        "punctuation.terminator",
        "meta.brace"
      ],
      "settings": {
        "foreground": "#9a9e9d",
        "fontStyle": ""
      }
    },
    {
      "name": "Decorators / Annotations",
      "scope": [
        "meta.decorator",
        "meta.decorator entity.name.function",
        "punctuation.decorator"
      ],
      "settings": {
        "foreground": "#00b5cc",
        "fontStyle": "italic"
      }
    },
    {
      "name": "CSS properties",
      "scope": [
        "support.type.property-name.css",
        "support.type.vendored.property-name.css"
      ],
      "settings": {
        "foreground": "#00b5cc",
        "fontStyle": ""
      }
    },
    {
      "name": "CSS selectors",
      "scope": [
        "entity.other.attribute-name.class.css",
        "entity.other.attribute-name.id.css"
      ],
      "settings": {
        "foreground": "#88b04b",
        "fontStyle": "bold"
      }
    },
    {
      "name": "CSS values",
      "scope": [
        "support.constant.property-value.css",
        "support.constant.color.css"
      ],
      "settings": {
        "foreground": "#76ff7b",
        "fontStyle": ""
      }
    },
    {
      "name": "CSS units",
      "scope": [
        "keyword.other.unit.css"
      ],
      "settings": {
        "foreground": "#8d7dac",
        "fontStyle": ""
      }
    },
    {
      "name": "JSON keys",
      "scope": [
        "support.type.property-name.json"
      ],
      "settings": {
        "foreground": "#00b5cc",
        "fontStyle": ""
      }
    },
    {
      "name": "Markdown headings",
      "scope": [
        "markup.heading",
        "markup.heading entity.name",
        "entity.name.section.markdown"
      ],
      "settings": {
        "foreground": "#9a9e9d",
        "fontStyle": "bold"
      }
    },
    {
      "name": "Markdown bold",
      "scope": [
        "markup.bold"
      ],
      "settings": {
        "foreground": "#76ff7b",
        "fontStyle": "bold"
      }
    },
    {
      "name": "Markdown italic",
      "scope": [
        "markup.italic"
      ],
      "settings": {
        "foreground": "#00b5cc",
        "fontStyle": "italic"
      }
    },
    {
      "name": "Markdown inline code",
      "scope": [
        "markup.inline.raw",
        "markup.raw"
      ],
      "settings": {
        "foreground": "#d94f70",
        "fontStyle": ""
      }
    },
    {
      "name": "Markdown links",
      "scope": [
        "markup.underline.link"
      ],
      "settings": {
        "foreground": "#decdbe",
        "fontStyle": ""
      }
    },
    {
      "name": "Markdown quotes",
      "scope": [
        "markup.quote"
      ],
      "settings": {
        "foreground": "#9a9e9d",
        "fontStyle": "italic"
      }
    },
    {
      "name": "Diff inserted",
      "scope": [
        "markup.inserted"
      ],
      "settings": {
        "foreground": "#88b04b"
      }
    },
    {
      "name": "Diff deleted",
      "scope": [
        "markup.deleted"
      ],
      "settings": {
        "foreground": "#dd4132"
      }
    },
    {
      "name": "Diff changed",
      "scope": [
        "markup.changed"
      ],
      "settings": {
        "foreground": "#efc050"
      }
    }
  ]
}