{
  "name": "Pantone Cornflower Blue (Light)",
  "type": "light",
  "semanticHighlighting": true,
  "semanticTokenColors": {
    "variable.declaration": {
      "foreground": "#0c1422"
    },
    "variable.readonly": {
      "foreground": "#8c690f",
      "bold": true
    },
    "parameter.declaration": {
      "foreground": "#0c1422",
      "italic": true
    },
    "function.declaration": {
      "foreground": "#007d62",
      "bold": true
    },
    "function.defaultLibrary": {
      "foreground": "#007d62"
    },
    "type": {
      "foreground": "#9e4fa5",
      "italic": true
    },
    "type.defaultLibrary": {
      "foreground": "#9e4fa5",
      "italic": true
    },
    "class": {
      "foreground": "#b8435f",
      "bold": true,
      "italic": true
    },
    "interface": {
      "foreground": "#9e4fa5",
      "italic": true
    },
    "enum": {
      "foreground": "#9e4fa5",
      "italic": true
    },
    "enumMember": {
      "foreground": "#8c690f",
      "bold": true
    },
    "namespace": {
      "foreground": "#9e4fa5"
    },
    "property.readonly": {
      "foreground": "#8c690f",
      "bold": true
    }
  },
  "colors": {
    "editor.background": "#f8f9fa",
    "editor.foreground": "#0c1422",
    "editorCursor.foreground": "#4d88e1",
    "editor.selectionBackground": "#4d88e133",
    "editor.inactiveSelectionBackground": "#4d88e11a",
    "editor.lineHighlightBackground": "#4d88e114",
    "editor.lineHighlightBorder": "#4d88e100",
    "editor.findMatchBackground": "#ffaa4d59",
    "editor.findMatchHighlightBackground": "#ffaa4d26",
    "editor.wordHighlightBackground": "#4d88e126",
    "editorBracketMatch.background": "#4d88e133",
    "editorBracketMatch.border": "#4d88e180",
    "editorIndentGuide.background": "#0c142214",
    "editorIndentGuide.activeBackground": "#0c14222e",
    "editorWhitespace.foreground": "#0c14221a",
    "editorRuler.foreground": "#0c142214",
    "editorLineNumber.foreground": "#7b95b8",
    "editorLineNumber.activeForeground": "#0c1422",
    "editorGutter.addedBackground": "#4e9a2f",
    "editorGutter.modifiedBackground": "#d4a017",
    "editorGutter.deletedBackground": "#bf1932",
    "editorError.foreground": "#bf1932",
    "editorWarning.foreground": "#d4a017",
    "editorInfo.foreground": "#de907d",
    "sideBar.background": "#f2f3f4",
    "sideBar.foreground": "#0c1422",
    "sideBar.border": "#cbd2d9",
    "sideBarTitle.foreground": "#0c1422",
    "sideBarSectionHeader.background": "#4d88e11a",
    "sideBarSectionHeader.foreground": "#0c1422",
    "activityBar.background": "#ebedef",
    "activityBar.foreground": "#4d88e1",
    "activityBar.inactiveForeground": "#7b95b8",
    "activityBar.border": "#cbd2d9",
    "activityBarBadge.background": "#de907d",
    "activityBarBadge.foreground": "#f7f7f7",
    "titleBar.activeBackground": "#f2f3f4",
    "titleBar.activeForeground": "#0c1422",
    "titleBar.inactiveBackground": "#f2f3f4",
    "titleBar.inactiveForeground": "#7b95b8",
    "titleBar.border": "#cbd2d9",
    "tab.activeBackground": "#f8f9fa",
    "tab.activeForeground": "#0c1422",
    "tab.inactiveBackground": "#f2f3f4",
    "tab.inactiveForeground": "#7b95b8",
    "tab.activeBorder": "#4d88e1",
    "tab.activeBorderTop": "#4d88e100",
    "tab.border": "#cbd2d9",
    "editorGroupHeader.tabsBackground": "#f2f3f4",
    "editorGroupHeader.tabsBorder": "#cbd2d9",
    "editorGroup.border": "#cbd2d9",
    "statusBar.background": "#4d88e1",
    "statusBar.foreground": "#0c1422",
    "statusBar.border": "#cbd2d9",
    "statusBar.debuggingBackground": "#de907d",
    "statusBar.debuggingForeground": "#f7f7f7",
    "statusBar.noFolderBackground": "#ebedef",
    "statusBarItem.hoverBackground": "#f7f7f733",
    "statusBarItem.remoteBackground": "#4174bf",
    "statusBarItem.remoteForeground": "#0c1422",
    "input.background": "#f8f9fa",
    "input.foreground": "#0c1422",
    "input.border": "#cbd2d9",
    "input.placeholderForeground": "#7b95b8",
    "inputOption.activeBorder": "#4d88e1",
    "inputValidation.errorBorder": "#bf1932",
    "inputValidation.warningBorder": "#d4a017",
    "inputValidation.infoBorder": "#de907d",
    "dropdown.background": "#f8f9fa",
    "dropdown.foreground": "#0c1422",
    "dropdown.border": "#cbd2d9",
    "list.activeSelectionBackground": "#4d88e133",
    "list.activeSelectionForeground": "#0c1422",
    "list.hoverBackground": "#4d88e11a",
    "list.inactiveSelectionBackground": "#4d88e11a",
    "list.focusBackground": "#4d88e126",
    "list.highlightForeground": "#4d88e1",
    "button.background": "#4d88e1",
    "button.foreground": "#0c1422",
    "button.hoverBackground": "#457acb",
    "button.secondaryBackground": "#ebedef",
    "button.secondaryForeground": "#0c1422",
    "badge.background": "#4d88e1",
    "badge.foreground": "#0c1422",
    "scrollbar.shadow": "#080e1614",
    "scrollbarSlider.background": "#0c14221a",
    "scrollbarSlider.hoverBackground": "#0c142233",
    "scrollbarSlider.activeBackground": "#0c14224d",
    "minimap.background": "#f8f9fa",
    "minimap.findMatchHighlight": "#ffaa4d80",
    "minimap.selectionHighlight": "#4d88e14d",
    "panel.background": "#f2f3f4",
    "panel.border": "#cbd2d9",
    "panelTitle.activeBorder": "#4d88e1",
    "panelTitle.activeForeground": "#0c1422",
    "panelTitle.inactiveForeground": "#7b95b8",
    "terminal.background": "#f2f3f4",
    "terminal.foreground": "#0c1422",
    "terminalCursor.foreground": "#4d88e1",
    "terminal.ansiBlack": "#0c1422",
    "terminal.ansiRed": "#bf1932",
    "terminal.ansiGreen": "#4e9a2f",
    "terminal.ansiYellow": "#d4a017",
    "terminal.ansiBlue": "#0f4c81",
    "terminal.ansiMagenta": "#8c3359",
    "terminal.ansiCyan": "#006e7f",
    "terminal.ansiWhite": "#f8f9fa",
    "terminal.ansiBrightBlack": "#7b95b8",
    "terminal.ansiBrightRed": "#dd4132",
    "terminal.ansiBrightGreen": "#88b04b",
    "terminal.ansiBrightYellow": "#efc050",
    "terminal.ansiBrightBlue": "#2c9fd9",
    "terminal.ansiBrightMagenta": "#b163a3",
    "terminal.ansiBrightCyan": "#45b5aa",
    "terminal.ansiBrightWhite": "#f7f7f7",
    "gitDecoration.addedResourceForeground": "#4e9a2f",
    "gitDecoration.modifiedResourceForeground": "#d4a017",
    "gitDecoration.deletedResourceForeground": "#bf1932",
    "gitDecoration.untrackedResourceForeground": "#4e9a2f",
    "gitDecoration.conflictingResourceForeground": "#dd4132",
    "gitDecoration.ignoredResourceForeground": "#7b95b8",
    "breadcrumb.foreground": "#7b95b8",
    "breadcrumb.focusForeground": "#0c1422",
    "breadcrumb.activeSelectionForeground": "#0c1422",
    "notifications.background": "#f8f9fa",
    "notifications.foreground": "#0c1422",
    "notificationLink.foreground": "#4d88e1",
    "peekView.border": "#4d88e1",
    "peekViewEditor.background": "#f2f3f4",
    "peekViewResult.background": "#ebedef",
    "peekViewTitle.background": "#f2f3f4",
    "editorWidget.background": "#f8f9fa",
    "editorWidget.border": "#cbd2d9",
    "editorSuggestWidget.selectedBackground": "#4d88e126",
    "focusBorder": "#4d88e180",
    "selection.background": "#4d88e133",
    "textLink.foreground": "#de907d",
    "textLink.activeForeground": "#c6806f",
    "progressBar.background": "#4d88e1",
    "icon.foreground": "#7b95b8",
    "descriptionForeground": "#7b95b8"
  },
  "tokenColors": [
    {
      "name": "Comments",
      "scope": [
        "comment",
        "comment.line",
        "comment.block",
        "comment.block.documentation",
        "punctuation.definition.comment"
      ],
      "settings": {
        "foreground": "#7b95b8",
        "fontStyle": "italic"
      }
    },
    {
      "name": "Keywords",
      "scope": [
        "keyword",
        "keyword.control",
        "keyword.control.conditional",
        "keyword.control.loop",
        "keyword.control.flow",
        "keyword.control.import",
        "keyword.control.export",
        "keyword.control.from"
      ],
      "settings": {
        "foreground": "#4173be",
        "fontStyle": "bold"
      }
    },
    {
      "name": "Keyword operators",
      "scope": [
        "keyword.operator.new",
        "keyword.operator.expression",
        "keyword.operator.instanceof",
        "keyword.operator.typeof",
        "keyword.operator.logical",
        "keyword.operator.delete"
      ],
      "settings": {
        "foreground": "#4173be",
        "fontStyle": "bold"
      }
    },
    {
      "name": "Storage type (class, function, var, let, const)",
      "scope": [
        "storage.type",
        "storage.modifier"
      ],
      "settings": {
        "foreground": "#4173be",
        "fontStyle": "bold"
      }
    },
    {
      "name": "Strings",
      "scope": [
        "string",
        "string.quoted",
        "string.quoted.single",
        "string.quoted.double",
        "string.quoted.triple",
        "string.template",
        "string.quoted.other"
      ],
      "settings": {
        "foreground": "#966155",
        "fontStyle": ""
      }
    },
    {
      "name": "String interpolation",
      "scope": [
        "string.interpolated",
        "punctuation.definition.template-expression",
        "punctuation.section.embedded"
      ],
      "settings": {
        "foreground": "#4173be",
        "fontStyle": ""
      }
    },
    {
      "name": "Regular expressions",
      "scope": [
        "string.regexp"
      ],
      "settings": {
        "foreground": "#966155",
        "fontStyle": ""
      }
    },
    {
      "name": "Numbers",
      "scope": [
        "constant.numeric",
        "constant.numeric.integer",
        "constant.numeric.float",
        "constant.numeric.hex"
      ],
      "settings": {
        "foreground": "#9b662f",
        "fontStyle": ""
      }
    },
    {
      "name": "Language constants (true, false, null)",
      "scope": [
        "constant.language",
        "constant.language.boolean",
        "constant.language.null",
        "constant.language.undefined"
      ],
      "settings": {
        "foreground": "#8c690f",
        "fontStyle": "bold"
      }
    },
    {
      "name": "Other constants (ALL_CAPS, enums)",
      "scope": [
        "variable.other.constant",
        "variable.other.enummember"
      ],
      "settings": {
        "foreground": "#8c690f",
        "fontStyle": "bold"
      }
    },
    {
      "name": "Escape characters",
      "scope": [
        "constant.character.escape"
      ],
      "settings": {
        "foreground": "#4b6fa5",
        "fontStyle": ""
      }
    },
    {
      "name": "Type names and interfaces",
      "scope": [
        "entity.name.type",
        "entity.name.type.class",
        "entity.name.type.interface",
        "entity.name.type.enum",
        "entity.name.type.alias",
        "entity.name.type.module",
        "support.type",
        "support.type.builtin"
      ],
      "settings": {
        "foreground": "#9e4fa5",
        "fontStyle": "italic"
      }
    },
    {
      "name": "Type parameters (generics <T>)",
      "scope": [
        "entity.name.type.parameter"
      ],
      "settings": {
        "foreground": "#9e4fa5",
        "fontStyle": "italic"
      }
    },
    {
      "name": "Function declarations",
      "scope": [
        "entity.name.function",
        "meta.function entity.name.function"
      ],
      "settings": {
        "foreground": "#007d62",
        "fontStyle": "bold"
      }
    },
    {
      "name": "Function calls",
      "scope": [
        "meta.function-call entity.name.function",
        "support.function"
      ],
      "settings": {
        "foreground": "#007d62",
        "fontStyle": ""
      }
    },
    {
      "name": "Method calls",
      "scope": [
        "meta.method-call entity.name.function",
        "entity.name.function.member"
      ],
      "settings": {
        "foreground": "#007d62",
        "fontStyle": ""
      }
    },
    {
      "name": "Variables",
      "scope": [
        "variable",
        "variable.other",
        "variable.other.readwrite"
      ],
      "settings": {
        "foreground": "#0c1422",
        "fontStyle": ""
      }
    },
    {
      "name": "Parameters",
      "scope": [
        "variable.parameter"
      ],
      "settings": {
        "foreground": "#0c1422",
        "fontStyle": "italic"
      }
    },
    {
      "name": "Language variables (this, self, super)",
      "scope": [
        "variable.language",
        "variable.language.this",
        "variable.language.self",
        "variable.language.super"
      ],
      "settings": {
        "foreground": "#4173be",
        "fontStyle": "italic"
      }
    },
    {
      "name": "Object properties",
      "scope": [
        "variable.other.property",
        "variable.other.object.property",
        "meta.object-literal.key"
      ],
      "settings": {
        "foreground": "#0c1422",
        "fontStyle": ""
      }
    },
    {
      "name": "Class names",
      "scope": [
        "entity.name.class",
        "entity.name.type.class",
        "support.class"
      ],
      "settings": {
        "foreground": "#b8435f",
        "fontStyle": "bold italic"
      }
    },
    {
      "name": "Inherited classes",
      "scope": [
        "entity.other.inherited-class"
      ],
      "settings": {
        "foreground": "#b8435f",
        "fontStyle": "italic"
      }
    },
    {
      "name": "HTML/XML tags",
      "scope": [
        "entity.name.tag",
        "punctuation.definition.tag"
      ],
      "settings": {
        "foreground": "#4173be",
        "fontStyle": "bold"
      }
    },
    {
      "name": "HTML/XML attributes",
      "scope": [
        "entity.other.attribute-name"
      ],
      "settings": {
        "foreground": "#007d62",
        "fontStyle": "italic"
      }
    },
    {
      "name": "Operators",
      "scope": [
        "keyword.operator",
        "keyword.operator.arithmetic",
        "keyword.operator.assignment",
        "keyword.operator.comparison",
        "keyword.operator.ternary"
      ],
      "settings": {
        "foreground": "#4b6fa5",
        "fontStyle": ""
      }
    },
    {
      "name": "Punctuation",
      "scope": [
        "punctuation",
        "punctuation.separator",
        "punctuation.terminator",
        "meta.brace"
      ],
      "settings": {
        "foreground": "#7b95b8",
        "fontStyle": ""
      }
    },
    {
      "name": "Decorators / Annotations",
      "scope": [
        "meta.decorator",
        "meta.decorator entity.name.function",
        "punctuation.decorator"
      ],
      "settings": {
        "foreground": "#9e4fa5",
        "fontStyle": "italic"
      }
    },
    {
      "name": "CSS properties",
      "scope": [
        "support.type.property-name.css",
        "support.type.vendored.property-name.css"
      ],
      "settings": {
        "foreground": "#9e4fa5",
        "fontStyle": ""
      }
    },
    {
      "name": "CSS selectors",
      "scope": [
        "entity.other.attribute-name.class.css",
        "entity.other.attribute-name.id.css"
      ],
      "settings": {
        "foreground": "#b8435f",
        "fontStyle": "bold"
      }
    },
    {
      "name": "CSS values",
      "scope": [
        "support.constant.property-value.css",
        "support.constant.color.css"
      ],
      "settings": {
        "foreground": "#8c690f",
        "fontStyle": ""
      }
    },
    {
      "name": "CSS units",
      "scope": [
        "keyword.other.unit.css"
      ],
      "settings": {
        "foreground": "#9b662f",
        "fontStyle": ""
      }
    },
    {
      "name": "JSON keys",
      "scope": [
        "support.type.property-name.json"
      ],
      "settings": {
        "foreground": "#9e4fa5",
        "fontStyle": ""
      }
    },
    {
      "name": "Markdown headings",
      "scope": [
        "markup.heading",
        "markup.heading entity.name",
        "entity.name.section.markdown"
      ],
      "settings": {
        "foreground": "#4173be",
        "fontStyle": "bold"
      }
    },
    {
      "name": "Markdown bold",
      "scope": [
        "markup.bold"
      ],
      "settings": {
        "foreground": "#8c690f",
        "fontStyle": "bold"
      }
    },
    {
      "name": "Markdown italic",
      "scope": [
        "markup.italic"
      ],
      "settings": {
        "foreground": "#9e4fa5",
        "fontStyle": "italic"
      }
    },
    {
      "name": "Markdown inline code",
      "scope": [
        "markup.inline.raw",
        "markup.raw"
      ],
      "settings": {
        "foreground": "#966155",
        "fontStyle": ""
      }
    },
    {
      "name": "Markdown links",
      "scope": [
        "markup.underline.link"
      ],
      "settings": {
        "foreground": "#007d62",
        "fontStyle": ""
      }
    },
    {
      "name": "Markdown quotes",
      "scope": [
        "markup.quote"
      ],
      "settings": {
        "foreground": "#7b95b8",
        "fontStyle": "italic"
      }
    },
    {
      "name": "Diff inserted",
      "scope": [
        "markup.inserted"
      ],
      "settings": {
        "foreground": "#88b04b"
      }
    },
    {
      "name": "Diff deleted",
      "scope": [
        "markup.deleted"
      ],
      "settings": {
        "foreground": "#dd4132"
      }
    },
    {
      "name": "Diff changed",
      "scope": [
        "markup.changed"
      ],
      "settings": {
        "foreground": "#efc050"
      }
    }
  ]
}